freckll/__init__.py
freckll/ace.py
freckll/chegp.py
freckll/constants.py
freckll/diffusion.py
freckll/distill.py
freckll/kinetics.py
freckll/log.py
freckll/main.py
freckll/nasa.py
freckll/ode.py
freckll/plot.py
freckll/species.py
freckll/taurex.py
freckll/types.py
freckll/utils.py
freckll/data/NASA.therm
freckll/data/__init__.py
freckll/data/new_nasa.therm
freckll/data/Sections/qyC2H2_1.dat
freckll/data/Sections/qyC2H3_1.dat
freckll/data/Sections/qyC2H4_1.dat
freckll/data/Sections/qyC2H4_2.dat
freckll/data/Sections/qyC2H6_1.dat
freckll/data/Sections/qyC2H6_2.dat
freckll/data/Sections/qyC2H6_3.dat
freckll/data/Sections/qyC2H6_4.dat
freckll/data/Sections/qyC2H6_5.dat
freckll/data/Sections/qyC2H_1.dat
freckll/data/Sections/qyC2N2_1.dat
freckll/data/Sections/qyCH2CO_1.dat
freckll/data/Sections/qyCH2S_1.dat
freckll/data/Sections/qyCH3CHO_1.dat
freckll/data/Sections/qyCH3CHO_2.dat
freckll/data/Sections/qyCH3OH_1.dat
freckll/data/Sections/qyCH3OH_2.dat
freckll/data/Sections/qyCH3OOH_1.dat
freckll/data/Sections/qyCH3SH_1.dat
freckll/data/Sections/qyCH3_1.dat
freckll/data/Sections/qyCH4_1.dat
freckll/data/Sections/qyCH4_2.dat
freckll/data/Sections/qyCH4_3.dat
freckll/data/Sections/qyCH4_4.dat
freckll/data/Sections/qyCH4_5.dat
freckll/data/Sections/qyCO2_1.dat
freckll/data/Sections/qyCO2_2.dat
freckll/data/Sections/qyCO2_3.dat
freckll/data/Sections/qyCO_1.dat
freckll/data/Sections/qyCO_2.dat
freckll/data/Sections/qyCS2_1.dat
freckll/data/Sections/qyCS_1.dat
freckll/data/Sections/qyH2CN_1.dat
freckll/data/Sections/qyH2CO_1.dat
freckll/data/Sections/qyH2CO_2.dat
freckll/data/Sections/qyH2CO_3.dat
freckll/data/Sections/qyH2O2_1.dat
freckll/data/Sections/qyH2O_1.dat
freckll/data/Sections/qyH2O_2.dat
freckll/data/Sections/qyH2O_3.dat
freckll/data/Sections/qyH2SO_1.dat
freckll/data/Sections/qyH2SO_2.dat
freckll/data/Sections/qyH2S_1.dat
freckll/data/Sections/qyH2_1.dat
freckll/data/Sections/qyH2_2.dat
freckll/data/Sections/qyHCN_1.dat
freckll/data/Sections/qyHCO_1.dat
freckll-0.0.1.dist-info/METADATA
freckll-0.0.1.dist-info/WHEEL
freckll-0.0.1.dist-info/entry_points.txt
freckll-0.0.1.dist-info/licenses/LICENSE
freckll-0.0.1.dist-info/RECORD
